red_cache/__init__.py
red_cache/_base.py
red_cache/_cache.py
red_cache/cache.py
red_cache/counter.py
red_cache/ex.py
red_cache/objects.py
red_cache/typing.py
red_cache-0.2.5.dist-info/LICENSE
red_cache-0.2.5.dist-info/METADATA
red_cache-0.2.5.dist-info/WHEEL
red_cache-0.2.5.dist-info/top_level.txt
red_cache-0.2.5.dist-info/RECORD
