Metadata-Version: 2.1
Name: red-cache
Version: 0.2.5
Summary: UNKNOWN
Home-page: https://gitee.com/irealing/red_cache
Author: Memory_Leak
Author-email: irealing@163.com
License: UNKNOWN
Platform: UNKNOWN
Requires-Dist: redis (>=3.0.1)
